bottle.py
cps110bottle-0.13.dev2.data/scripts/bottle.py
cps110bottle-0.13.dev2.dist-info/DESCRIPTION.rst
cps110bottle-0.13.dev2.dist-info/METADATA
cps110bottle-0.13.dev2.dist-info/RECORD
cps110bottle-0.13.dev2.dist-info/WHEEL
cps110bottle-0.13.dev2.dist-info/metadata.json
cps110bottle-0.13.dev2.dist-info/top_level.txt
