Metadata-Version: 2.0
Name: cps110bottle
Version: 0.13.dev2
Summary: A minor modification to the Python bottle framework suitable for student use.
Home-page: http://bottlepy.org/
Author: Marcel Hellkamp
Author-email: sschaub@gmail.com
License: MIT
Platform: any
Classifier: Development Status :: 4 - Beta
Classifier: Intended Audience :: Developers
Classifier: License :: OSI Approved :: MIT License
Classifier: Topic :: Internet :: WWW/HTTP :: Dynamic Content :: CGI Tools/Libraries
Classifier: Topic :: Internet :: WWW/HTTP :: HTTP Servers
Classifier: Topic :: Internet :: WWW/HTTP :: WSGI
Classifier: Topic :: Internet :: WWW/HTTP :: WSGI :: Application
Classifier: Topic :: Internet :: WWW/HTTP :: WSGI :: Middleware
Classifier: Topic :: Internet :: WWW/HTTP :: WSGI :: Server
Classifier: Topic :: Software Development :: Libraries :: Application Frameworks
Classifier: Programming Language :: Python :: 2.7
Classifier: Programming Language :: Python :: 3
Classifier: Programming Language :: Python :: 3.2
Classifier: Programming Language :: Python :: 3.3
Classifier: Programming Language :: Python :: 3.4
Classifier: Programming Language :: Python :: 3.5
